jinja2_orcid_extension/__init__.py
jinja2_orcid_extension/jinja2_orcid_extension.py
jinja2_orcid_extension-0.1.0.dev1.dist-info/AUTHORS.rst
jinja2_orcid_extension-0.1.0.dev1.dist-info/LICENSE
jinja2_orcid_extension-0.1.0.dev1.dist-info/METADATA
jinja2_orcid_extension-0.1.0.dev1.dist-info/WHEEL
jinja2_orcid_extension-0.1.0.dev1.dist-info/top_level.txt
jinja2_orcid_extension-0.1.0.dev1.dist-info/RECORD
