Metadata-Version: 2.1
Name: jinja2-orcid-extension
Version: 0.1.0.dev1
Summary: Jinja2 extension with custom filtersreplacing ORCIDs with elements from the orcid records.
Home-page: https://gitlab.com/uantwerpen-rdm-support/jinja2_orcid_extension
Author: Maarten Vermeyen
Author-email: maarten@vermeyen.xyz
License: MIT license
Keywords: jinja2_orcid_extension
Platform: UNKNOWN
Classifier: Development Status :: 2 - Pre-Alpha
Classifier: Intended Audience :: Developers
Classifier: License :: OSI Approved :: MIT License
Classifier: Natural Language :: English
Classifier: Programming Language :: Python :: 3
Classifier: Programming Language :: Python :: 3.6
Classifier: Programming Language :: Python :: 3.7
Classifier: Programming Language :: Python :: 3.8
Requires-Python: >=3.6
License-File: LICENSE
License-File: AUTHORS.rst
Requires-Dist: requests (>=2)
Requires-Dist: requests-cache (>=0.9.3)
Requires-Dist: jinja2 (>=3)
